s3_radar/__init__.py
s3_radar/__main__.py
s3_radar/constants.py
s3_radar/data_generator.py
s3_radar/s3_client.py
s3_radar-0.1.5.dist-info/LICENSE
s3_radar-0.1.5.dist-info/METADATA
s3_radar-0.1.5.dist-info/WHEEL
s3_radar-0.1.5.dist-info/entry_points.txt
s3_radar-0.1.5.dist-info/RECORD
